hardware/fpga/epistemic_power_accumulator.v
// GENERATED_FROM_STDLIB: stdlib/hardware/kaxi.sio
// GENERATED_BY: self-hosted/compiler/codegen/hardware/kaxi_emitter.sio
// Sounio Omega - Hardware Epistemic Power accumulator
// Aggregates hardware counter increments and exposes live log-space score (Q32.32).

`timescale 1ns/1ps

module epistemic_power_accumulator #(
    parameter SCALE_SHIFT = 30
) (
    input  wire         aclk,
    input  wire         aresetn,

    // Counter deltas from epistemic fabric.
    input  wire [31:0]  fidelity_inc,
    input  wire [31:0]  prov_depth_inc,
    input  wire [31:0]  quantum_fidelity_inc,
    input  wire [31:0]  quantum_controller_inc,

    input  wire         clear_counters,

    // Q32.32 log-space approximation.
    output reg  [63:0]  epistemic_power_log,
    output reg  [31:0]  total_transactions
);

    reg [63:0] fidelity_accum;
    reg [63:0] prov_accum;
    reg [63:0] quantum_accum;

    wire [63:0] fidelity_inc64 = {32'd0, fidelity_inc};
    wire [63:0] prov_inc64 = {32'd0, prov_depth_inc};
    wire [63:0] quantum_inc64 = {32'd0, quantum_fidelity_inc};
    wire [63:0] quantum_controller_inc64 = {32'd0, quantum_controller_inc};

    wire [63:0] fidelity_next = fidelity_accum + fidelity_inc64;
    wire [63:0] prov_next = prov_accum + prov_inc64;
    wire [63:0] quantum_next = quantum_accum + quantum_inc64 + quantum_controller_inc64;

    wire [63:0] weighted_log_next =
        (fidelity_next >> 3) + // runtime+gum dominant lane
        (prov_next >> 4) +     // provenance lane
        (quantum_next >> 5);   // quantum lane

    wire tx_seen = |fidelity_inc;

    always @(posedge aclk or negedge aresetn) begin
        if (!aresetn) begin
            fidelity_accum <= 64'd0;
            prov_accum <= 64'd0;
            quantum_accum <= 64'd0;
            total_transactions <= 32'd0;
            epistemic_power_log <= 64'd0;
        end else if (clear_counters) begin
            fidelity_accum <= 64'd0;
            prov_accum <= 64'd0;
            quantum_accum <= 64'd0;
            total_transactions <= 32'd0;
            epistemic_power_log <= 64'd0;
        end else begin
            fidelity_accum <= fidelity_next;
            prov_accum <= prov_next;
            quantum_accum <= quantum_next;
            total_transactions <= total_transactions + {31'd0, tx_seen};
            epistemic_power_log <= weighted_log_next;
        end
    end

endmodule

hardware/fpga/tb_epistemic_power_accumulator.v
`timescale 1ns/1ps

module tb_epistemic_power_accumulator;
    reg clk;
    reg rst_n;
    reg [31:0] fidelity_inc;
    reg [31:0] prov_depth_inc;
    reg [31:0] quantum_fidelity_inc;
    reg [31:0] quantum_controller_inc;
    reg clear_counters;

    wire [63:0] epistemic_power_log;
    wire [31:0] total_transactions;

    integer failures;
    reg [63:0] expected_log;
    reg [1023:0] dumpfile_path;

    epistemic_power_accumulator dut (
        .aclk(clk),
        .aresetn(rst_n),
        .fidelity_inc(fidelity_inc),
        .prov_depth_inc(prov_depth_inc),
        .quantum_fidelity_inc(quantum_fidelity_inc),
        .quantum_controller_inc(quantum_controller_inc),
        .clear_counters(clear_counters),
        .epistemic_power_log(epistemic_power_log),
        .total_transactions(total_transactions)
    );

    always #5 clk = ~clk;

    task expect_true;
        input cond;
        input [255:0] msg;
        begin
            if (!cond) begin
                $display("FAIL %0s", msg);
                failures = failures + 1;
            end
        end
    endtask

    initial begin
        if (!$value$plusargs("dumpfile=%s", dumpfile_path)) begin
            dumpfile_path = "artifacts/fpga/waveforms/tb_epistemic_power_accumulator.vcd";
        end
        $dumpfile(dumpfile_path);
        $dumpvars(0, tb_epistemic_power_accumulator);

        clk = 1'b0;
        rst_n = 1'b0;
        fidelity_inc = 32'd0;
        prov_depth_inc = 32'd0;
        quantum_fidelity_inc = 32'd0;
        quantum_controller_inc = 32'd0;
        clear_counters = 1'b0;
        failures = 0;
        expected_log = 64'd0;

        #20;
        rst_n = 1'b1;
        #10;

        // TX1
        fidelity_inc = 32'd8;
        prov_depth_inc = 32'd4;
        quantum_fidelity_inc = 32'd2;
        quantum_controller_inc = 32'd30;
        #10;
        expected_log = ((64'd8 >> 3) + (64'd4 >> 4) + ((64'd2 + 64'd30) >> 5));
        expect_true(epistemic_power_log == expected_log, "tx1 weighted log");
        expect_true(total_transactions == 32'd1, "tx1 transaction count");

        // TX2
        fidelity_inc = 32'd16;
        prov_depth_inc = 32'd16;
        quantum_fidelity_inc = 32'd32;
        quantum_controller_inc = 32'd32;
        #10;
        expected_log = ((64'd24 >> 3) + (64'd20 >> 4) + (64'd96 >> 5));
        expect_true(epistemic_power_log == expected_log, "tx2 weighted log");
        expect_true(total_transactions == 32'd2, "tx2 transaction count");

        // clear path
        clear_counters = 1'b1;
        fidelity_inc = 32'd0;
        prov_depth_inc = 32'd0;
        quantum_fidelity_inc = 32'd0;
        quantum_controller_inc = 32'd0;
        #10;
        clear_counters = 1'b0;
        #10;
        expect_true(epistemic_power_log == 64'd0, "clear resets log");
        expect_true(total_transactions == 32'd0, "clear resets transactions");

        if (failures != 0) begin
            $display("FAIL tb_epistemic_power_accumulator cases=%0d", failures);
            $finish(1);
        end

        $display("OMEGA_COUNTERS accum_log=%0d accum_tx=%0d", epistemic_power_log, total_transactions);
        $display("PASS tb_epistemic_power_accumulator");
        $finish(0);
    end
endmodule

artifacts/fpga/waveforms/tb_epistemic_power_accumulator.vcd
$date
	Thu Feb 26 08:43:49 2026
$end
$version
	Icarus Verilog
$end
$timescale
	1ps
$end
$scope module tb_epistemic_power_accumulator $end
$var wire 32 ! total_transactions [31:0] $end
$var wire 64 " epistemic_power_log [63:0] $end
$var reg 1 # clear_counters $end
$var reg 1 $ clk $end
$var reg 1024 % dumpfile_path [1023:0] $end
$var reg 64 & expected_log [63:0] $end
$var reg 32 ' fidelity_inc [31:0] $end
$var reg 32 ( prov_depth_inc [31:0] $end
$var reg 32 ) quantum_controller_inc [31:0] $end
$var reg 32 * quantum_fidelity_inc [31:0] $end
$var reg 1 + rst_n $end
$var integer 32 , failures [31:0] $end
$scope module dut $end
$var wire 1 $ aclk $end
$var wire 1 + aresetn $end
$var wire 1 # clear_counters $end
$var wire 32 - fidelity_inc [31:0] $end
$var wire 32 . prov_depth_inc [31:0] $end
$var wire 32 / quantum_controller_inc [31:0] $end
$var wire 32 0 quantum_fidelity_inc [31:0] $end
$var wire 64 1 weighted_log_next [63:0] $end
$var wire 1 2 tx_seen $end
$var wire 64 3 quantum_next [63:0] $end
$var wire 64 4 quantum_inc64 [63:0] $end
$var wire 64 5 quantum_controller_inc64 [63:0] $end
$var wire 64 6 prov_next [63:0] $end
$var wire 64 7 prov_inc64 [63:0] $end
$var wire 64 8 fidelity_next [63:0] $end
$var wire 64 9 fidelity_inc64 [63:0] $end
$var parameter 32 : SCALE_SHIFT $end
$var reg 64 ; epistemic_power_log [63:0] $end
$var reg 64 < fidelity_accum [63:0] $end
$var reg 64 = prov_accum [63:0] $end
$var reg 64 > quantum_accum [63:0] $end
$var reg 32 ? total_transactions [31:0] $end
$upscope $end
$scope task expect_true $end
$var reg 1 @ cond $end
$var reg 256 A msg [255:0] $end
$upscope $end
$upscope $end
$enddefinitions $end
$comment Show the parameter values. $end
$dumpall
b11110 :
$end
#0
$dumpvars
bx A
x@
b0 ?
b0 >
b0 =
b0 <
b0 ;
b0 9
b0 8
b0 7
b0 6
b0 5
b0 4
b0 3
02
b0 1
b0 0
b0 /
b0 .
b0 -
b0 ,
0+
b0 *
b0 )
b0 (
b0 '
b0 &
b110000101110010011101000110100101100110011000010110001101110100011100110010111101100110011100000110011101100001001011110111011101100001011101100110010101100110011011110111001001101101011100110010111101110100011000100101111101100101011100000110100101110011011101000110010101101101011010010110001101011111011100000110111101110111011001010111001001011111011000010110001101100011011101010110110101110101011011000110000101110100011011110111001000101110011101100110001101100100 %
0$
0#
b0 "
b0 !
$end
#5000
1$
#10000
0$
#15000
1$
#20000
0$
1+
#25000
1$
#30000
b10 1
0$
b11110 5
b11110 )
b11110 /
b100000 3
b10 4
b10 *
b10 0
b100 6
b100 7
b100 (
b100 .
b1000 8
b1000 9
12
b1000 '
b1000 -
#35000
b100 1
b10 "
b10 ;
b1 !
b1 ?
b1000000 3
b100000 >
b1000 6
b100 =
b10000 8
b1000 <
1$
#40000
b111 1
0$
b100000 5
b100000 )
b100000 /
b1100000 3
b100000 4
b100000 *
b100000 0
b10100 6
b10000 7
b10000 (
b10000 .
b11000 8
b10000 9
b10000 '
b10000 -
b11101000111100000110001001000000111010001110010011000010110111001110011011000010110001101110100011010010110111101101110001000000110001101101111011101010110111001110100 A
1@
b10 &
#45000
b1100 1
b111 "
b111 ;
b10 !
b10 ?
b10100000 3
b1100000 >
b100100 6
b10100 =
b101000 8
b11000 <
1$
#50000
b111 1
0$
b0 5
b0 )
b0 /
b1100000 3
b0 4
b0 *
b0 0
b10100 6
b0 7
b0 (
b0 .
b11000 8
b0 9
02
b0 '
b0 -
1#
b11101000111100000110010001000000111010001110010011000010110111001110011011000010110001101110100011010010110111101101110001000000110001101101111011101010110111001110100 A
b111 &
#55000
b0 1
b0 "
b0 ;
b0 !
b0 ?
b0 3
b0 >
b0 6
b0 =
b0 8
b0 <
1$
#60000
0$
0#
#65000
1$
#70000
0$
b1100011011011000110010101100001011100100010000001110010011001010111001101100101011101000111001100100000011101000111001001100001011011100111001101100001011000110111010001101001011011110110111001110011 A
