hardware/fpga/k_axi_slave_epistemic.v
// GENERATED_FROM_STDLIB: stdlib/hardware/kaxi.sio
// GENERATED_BY: self-hosted/compiler/codegen/hardware/kaxi_emitter.sio
// Sounio Omega - K-AXI epistemic slave/propagation engine
// Consumes AXI-Stream value + epistemic sideband and applies hardware-side updates.

`timescale 1ns/1ps

module k_axi_merkle_core #(
    parameter PROV_WIDTH = 256
) (
    input  wire [PROV_WIDTH-1:0] in_prov,
    input  wire [63:0]           in_value,
    input  wire [31:0]           in_flags,
    output wire [PROV_WIDTH-1:0] digest
);
    localparam [255:0] PROV_SALT = 256'h4B5F4158495F4D45524B4C455F4550495354454D49435F4255535F7631A5A5A5;

    // Dedicated deterministic Merkle-seed fold (replace with hash core in v2).
    assign digest = {in_prov[247:0], in_prov[255:248]}
        ^ {192'd0, in_value}
        ^ {224'd0, in_flags}
        ^ PROV_SALT;
endmodule

module k_axi_slave_epistemic #(
    parameter DATA_WIDTH = 64,
    parameter VAR_WIDTH = 64,
    parameter PROV_WIDTH = 256,
    parameter CONF_WIDTH = 128,
    parameter FLAGS_WIDTH = 32,
    parameter SCALE_SHIFT = 30
) (
    input  wire                         aclk,
    input  wire                         aresetn,

    // AXI-Stream input.
    input  wire [DATA_WIDTH-1:0]        s_tdata,
    input  wire [VAR_WIDTH+PROV_WIDTH+CONF_WIDTH+FLAGS_WIDTH-1:0] s_tuser,
    input  wire                         s_tvalid,
    output wire                         s_tready,

    // Downstream interface.
    output reg  [DATA_WIDTH-1:0]        out_value,
    output reg  [VAR_WIDTH-1:0]         out_variance,
    output reg  [PROV_WIDTH-1:0]        out_prov,
    output reg  [CONF_WIDTH-1:0]        out_conf,
    output reg  [FLAGS_WIDTH-1:0]       out_flags,
    output reg                          out_valid,
    input  wire                         downstream_ready,

    // Merkle lane interface (optional external provenance core).
    input  wire                         merkle_lane_valid,
    input  wire [PROV_WIDTH-1:0]        merkle_lane_digest,
    output reg                          merkle_lane_req,
    output reg  [PROV_WIDTH-1:0]        merkle_lane_seed,

    // Epistemic Power accounting lanes.
    output reg  [31:0]                  gum_fidelity_inc,
    output reg  [31:0]                  provenance_depth_inc,
    output reg  [31:0]                  formal_coverage_inc
);

    localparam KUSER_WIDTH = VAR_WIDTH + PROV_WIDTH + CONF_WIDTH + FLAGS_WIDTH;

    localparam OP_PASS = 4'h0;
    localparam OP_ADD = 4'h1;
    localparam OP_MUL = 4'h2;
    localparam OP_DIV = 4'h3;
    localparam OP_FMA = 4'h4;

    wire accept;
    assign s_tready = !out_valid || downstream_ready;
    assign accept = s_tvalid && s_tready;

    wire [63:0] in_variance = s_tuser[63:0];
    wire [255:0] in_prov = s_tuser[319:64];
    wire [127:0] in_conf = s_tuser[447:320];
    wire [31:0] in_flags = s_tuser[479:448];

    wire [3:0] op_kind = in_flags[3:0];
    wire [7:0] failure_inc = in_flags[15:8];
    wire [7:0] success_inc = in_flags[23:16];
    wire [7:0] alpha_q8 = in_flags[31:24];

    wire [63:0] in_alpha = in_conf[127:64];
    wire [63:0] in_beta = in_conf[63:0];
    wire [63:0] alpha_next_wire = in_alpha + {56'd0, success_inc};
    wire [63:0] beta_next_wire = in_beta + {56'd0, failure_inc};
    wire [255:0] merkle_core_digest;

    k_axi_merkle_core #(
        .PROV_WIDTH(PROV_WIDTH)
    ) u_merkle_core (
        .in_prov(in_prov),
        .in_value(s_tdata),
        .in_flags(in_flags),
        .digest(merkle_core_digest)
    );

    reg [63:0] op_var;
    reg [127:0] degradation_full;
    reg [63:0] degradation_var;

    always @(*) begin
        // Richer op-sensitive variance profile (Q32.32-oriented approximation).
        // This keeps deterministic hardware semantics while differentiating
        // additive vs multiplicative/divisive uncertainty growth.
        case (op_kind)
            OP_ADD: op_var = in_variance + (in_variance >> 3);                         // +12.5%
            OP_MUL: op_var = in_variance + (in_variance >> 1) + (in_variance >> 3);   // +62.5%
            OP_DIV: op_var = in_variance + (in_variance >> 1) + (in_variance >> 2);   // +75.0%
            OP_FMA: op_var = in_variance + (in_variance >> 1) + (in_variance >> 2) + (in_variance >> 4); // +81.25%
            default: op_var = in_variance;
        endcase

        // Epistemic degradation term from alpha_q8 (Q0.8), now applied after
        // op-profile shaping so downstream sees profile+degradation.
        degradation_full = op_var * alpha_q8;
        degradation_var = degradation_full[71:8];
    end

    always @(posedge aclk or negedge aresetn) begin
        if (!aresetn) begin
            out_value <= {DATA_WIDTH{1'b0}};
            out_variance <= {VAR_WIDTH{1'b0}};
            out_prov <= {PROV_WIDTH{1'b0}};
            out_conf <= {CONF_WIDTH{1'b0}};
            out_flags <= {FLAGS_WIDTH{1'b0}};
            out_valid <= 1'b0;
            merkle_lane_req <= 1'b0;
            merkle_lane_seed <= {PROV_WIDTH{1'b0}};
            gum_fidelity_inc <= 32'd0;
            provenance_depth_inc <= 32'd0;
            formal_coverage_inc <= 32'd0;
        end else begin
            // One-cycle request pulse unless a transaction is accepted.
            merkle_lane_req <= 1'b0;

            if (out_valid && downstream_ready) begin
                out_valid <= 1'b0;
            end

            if (accept) begin
                out_value <= s_tdata;
                out_variance <= op_var + degradation_var;
                out_flags <= in_flags;

                // Main path consumes dedicated Merkle-core digest.
                merkle_lane_seed <= merkle_core_digest;
                merkle_lane_req <= 1'b1;
                if (merkle_lane_valid) begin
                    out_prov <= merkle_lane_digest;
                end else begin
                    out_prov <= merkle_core_digest;
                end
                out_conf <= {alpha_next_wire, beta_next_wire};

                gum_fidelity_inc <= gum_fidelity_inc + 32'd1;
                provenance_depth_inc <= provenance_depth_inc + 32'd1;
                formal_coverage_inc <= formal_coverage_inc + 32'd1;

                out_valid <= 1'b1;
            end
        end
    end

endmodule

hardware/fpga/k_axi_master.v
// Sounio Omega - K-AXI master wrapper
// Streams Knowledge<T> payloads over AXI-Stream with epistemic metadata in TUSER.

`timescale 1ns/1ps

module k_axi_master #(
    parameter DATA_WIDTH = 64,
    parameter VAR_WIDTH = 64,
    parameter PROV_WIDTH = 256,
    parameter CONF_WIDTH = 128,
    parameter FLAGS_WIDTH = 32
) (
    input  wire                         s_axi_aclk,
    input  wire                         s_axi_aresetn,

    output reg  [DATA_WIDTH-1:0]        s_axi_tdata,
    output reg  [VAR_WIDTH+PROV_WIDTH+CONF_WIDTH+FLAGS_WIDTH-1:0] s_axi_tuser,
    output reg                          s_axi_tvalid,
    input  wire                         s_axi_tready,

    // Knowledge payload from PTX/runtime side.
    input  wire [63:0]                  k_value,
    input  wire [63:0]                  k_variance,
    input  wire [255:0]                 k_prov,
    input  wire [127:0]                 k_conf,
    input  wire [31:0]                  k_flags,

    input  wire                         start_transaction,
    output reg                          transaction_done,

    // Increment signal consumed by EpistemicPower accounting.
    output reg  [31:0]                  fidelity_increment
);

    localparam KUSER_WIDTH = VAR_WIDTH + PROV_WIDTH + CONF_WIDTH + FLAGS_WIDTH;
    reg pending;

    always @(posedge s_axi_aclk or negedge s_axi_aresetn) begin
        if (!s_axi_aresetn) begin
            s_axi_tdata <= {DATA_WIDTH{1'b0}};
            s_axi_tuser <= {KUSER_WIDTH{1'b0}};
            s_axi_tvalid <= 1'b0;
            transaction_done <= 1'b0;
            fidelity_increment <= 32'd0;
            pending <= 1'b0;
        end else begin
            transaction_done <= 1'b0;
            fidelity_increment <= 32'd0;

            // Launch a new transaction if link is idle.
            if (start_transaction && !pending && !s_axi_tvalid) begin
                s_axi_tdata <= k_value;
                s_axi_tuser <= {k_flags, k_conf, k_prov, k_variance};
                s_axi_tvalid <= 1'b1;
                pending <= 1'b1;
            end

            // Complete handshake and emit one-shot accounting increment.
            if (s_axi_tvalid && s_axi_tready) begin
                s_axi_tvalid <= 1'b0;
                pending <= 1'b0;
                transaction_done <= 1'b1;
                fidelity_increment <= 32'd1;
            end
        end
    end

endmodule

hardware/fpga/tb_k_axi_bridge.v
`timescale 1ns/1ps

module tb_k_axi_bridge;
    reg clk;
    reg rst_n;

    reg [63:0] k_value;
    reg [63:0] k_variance;
    reg [255:0] k_prov;
    reg [127:0] k_conf;
    reg [31:0] k_flags;
    reg start_transaction;

    wire [63:0] s_tdata;
    wire [479:0] s_tuser;
    wire s_tvalid;
    wire s_tready;
    wire transaction_done;
    wire [31:0] fidelity_increment;

    wire [63:0] out_value;
    wire [63:0] out_variance;
    wire [255:0] out_prov;
    wire [127:0] out_conf;
    wire [31:0] out_flags;
    wire out_valid;
    reg downstream_ready;
    wire [31:0] gum_fidelity_inc;
    wire [31:0] provenance_depth_inc;
    wire [31:0] formal_coverage_inc;
    reg merkle_lane_valid;
    reg [255:0] merkle_lane_digest;
    wire merkle_lane_req;
    wire [255:0] merkle_lane_seed;

    integer failures;
    reg [63:0] conf_alpha;
    reg [63:0] conf_beta;
    reg [63:0] expected_var;
    reg [255:0] expected_merkle_seed;
    reg seen_transaction_done;
    reg seen_fidelity_pulse;
    reg seen_merkle_req;
    reg [1023:0] dumpfile_path;

    localparam [255:0] PROV_SALT = 256'h4B5F4158495F4D45524B4C455F4550495354454D49435F4255535F7631A5A5A5;

    always @(posedge clk) begin
        if (!rst_n) begin
            seen_transaction_done <= 1'b0;
            seen_fidelity_pulse <= 1'b0;
            seen_merkle_req <= 1'b0;
        end else begin
            if (transaction_done) begin
                seen_transaction_done <= 1'b1;
            end
            if (fidelity_increment != 32'd0) begin
                seen_fidelity_pulse <= 1'b1;
            end
            if (merkle_lane_req) begin
                seen_merkle_req <= 1'b1;
            end
        end
    end

    k_axi_master u_master (
        .s_axi_aclk(clk),
        .s_axi_aresetn(rst_n),
        .s_axi_tdata(s_tdata),
        .s_axi_tuser(s_tuser),
        .s_axi_tvalid(s_tvalid),
        .s_axi_tready(s_tready),
        .k_value(k_value),
        .k_variance(k_variance),
        .k_prov(k_prov),
        .k_conf(k_conf),
        .k_flags(k_flags),
        .start_transaction(start_transaction),
        .transaction_done(transaction_done),
        .fidelity_increment(fidelity_increment)
    );

    k_axi_slave_epistemic u_slave (
        .aclk(clk),
        .aresetn(rst_n),
        .s_tdata(s_tdata),
        .s_tuser(s_tuser),
        .s_tvalid(s_tvalid),
        .s_tready(s_tready),
        .out_value(out_value),
        .out_variance(out_variance),
        .out_prov(out_prov),
        .out_conf(out_conf),
        .out_flags(out_flags),
        .out_valid(out_valid),
        .downstream_ready(downstream_ready),
        .merkle_lane_valid(merkle_lane_valid),
        .merkle_lane_digest(merkle_lane_digest),
        .merkle_lane_req(merkle_lane_req),
        .merkle_lane_seed(merkle_lane_seed),
        .gum_fidelity_inc(gum_fidelity_inc),
        .provenance_depth_inc(provenance_depth_inc),
        .formal_coverage_inc(formal_coverage_inc)
    );

    always #5 clk = ~clk;

    task expect_true;
        input cond;
        input [255:0] msg;
        begin
            if (!cond) begin
                $display("FAIL %0s", msg);
                failures = failures + 1;
            end
        end
    endtask

    initial begin
        if (!$value$plusargs("dumpfile=%s", dumpfile_path)) begin
            dumpfile_path = "artifacts/fpga/waveforms/tb_k_axi_bridge.vcd";
        end
        $dumpfile(dumpfile_path);
        $dumpvars(0, tb_k_axi_bridge);

        clk = 1'b0;
        rst_n = 1'b0;
        k_value = 64'd0;
        k_variance = 64'd0;
        k_prov = 256'd0;
        k_conf = 128'd0;
        k_flags = 32'd0;
        start_transaction = 1'b0;
        downstream_ready = 1'b0;
        merkle_lane_valid = 1'b0;
        merkle_lane_digest = 256'd0;
        failures = 0;
        seen_transaction_done = 1'b0;
        seen_fidelity_pulse = 1'b0;
        seen_merkle_req = 1'b0;

        #20;
        rst_n = 1'b1;
        #10;

        // TX1: OP_ADD with alpha_q8=8, success=2, failure=1
        k_value = 64'd4096;
        k_variance = 64'd64;
        k_prov = 256'h1234_5678_9ABC_DEF0_1111_2222_3333_4444_5555_6666_7777_8888_9999_AAAA_BBBB_CCCC;
        k_conf = {64'd40, 64'd70};
        k_flags = {8'd8, 8'd2, 8'd1, 4'd0, 4'd1};
        start_transaction = 1'b1;
        #10;
        start_transaction = 1'b0;

        #20;
        expected_var = (k_variance + (k_variance >> 3));
        expected_var = expected_var + ((expected_var * 8) >> 8);
        expect_true(out_valid == 1'b1, "tx1 out_valid asserted");
        expect_true(seen_transaction_done == 1'b1, "tx1 transaction_done pulse");
        expect_true(seen_fidelity_pulse == 1'b1, "tx1 master fidelity increment");
        expect_true(out_value == k_value, "tx1 value forwarded");
        expect_true(out_variance == expected_var, "tx1 variance exact");
        expect_true(out_prov != k_prov, "tx1 provenance merged");
        expect_true(out_flags == k_flags, "tx1 flags forwarded");
        conf_alpha = out_conf[127:64];
        conf_beta = out_conf[63:0];
        expect_true(conf_alpha == 64'd42, "tx1 alpha incremented");
        expect_true(conf_beta == 64'd71, "tx1 beta incremented");
        expect_true(gum_fidelity_inc == 32'd1, "tx1 gum counter");
        expect_true(provenance_depth_inc == 32'd1, "tx1 provenance counter");
        expect_true(formal_coverage_inc == 32'd1, "tx1 formal counter");

        // Drain first packet so next transfer can proceed.
        downstream_ready = 1'b1;
        #10;
        downstream_ready = 1'b0;
        seen_transaction_done = 1'b0;
        seen_fidelity_pulse = 1'b0;
        seen_merkle_req = 1'b0;

        // TX2: OP_FMA with larger alpha_q8 degradation.
        k_value = 64'd68719476736; // 2^36
        k_variance = 64'd256;
        k_conf = {64'd100, 64'd200};
        k_flags = {8'd16, 8'd3, 8'd0, 4'd0, 4'd4};
        start_transaction = 1'b1;
        #10;
        start_transaction = 1'b0;

        #20;
        expected_var = (k_variance + (k_variance >> 1) + (k_variance >> 2) + (k_variance >> 4));
        expected_var = expected_var + ((expected_var * 16) >> 8);
        expect_true(out_valid == 1'b1, "slave out_valid asserted");
        expect_true(seen_transaction_done == 1'b1, "tx2 transaction_done pulse");
        expect_true(seen_fidelity_pulse == 1'b1, "tx2 master fidelity increment");
        expect_true(out_value == k_value, "tx2 value forwarded");
        expect_true(out_variance == expected_var, "tx2 variance exact");
        expect_true(out_flags == k_flags, "tx2 flags forwarded");
        conf_alpha = out_conf[127:64];
        conf_beta = out_conf[63:0];
        expect_true(conf_alpha == 64'd103, "tx2 alpha incremented");
        expect_true(conf_beta == 64'd200, "tx2 beta unchanged");

        expect_true(gum_fidelity_inc == 32'd2, "tx2 gum counter incremented");
        expect_true(provenance_depth_inc == 32'd2, "tx2 provenance counter incremented");
        expect_true(formal_coverage_inc == 32'd2, "tx2 formal counter incremented");

        // Drain second packet so Merkle-lane TX can proceed.
        downstream_ready = 1'b1;
        #10;
        downstream_ready = 1'b0;
        seen_transaction_done = 1'b0;
        seen_fidelity_pulse = 1'b0;
        seen_merkle_req = 1'b0;

        // TX3: Inject provenance from Merkle lane when valid.
        k_value = 64'd123456;
        k_variance = 64'd32;
        k_prov = 256'hDEAD_BEEF_0001_0002_0003_0004_0005_0006_0007_0008_0009_000A_000B_000C_000D_000E;
        k_conf = {64'd55, 64'd89};
        k_flags = {8'd4, 8'd1, 8'd1, 4'd0, 4'd2};
        merkle_lane_digest = 256'hCAFE_BABE_1111_2222_3333_4444_5555_6666_7777_8888_9999_AAAA_BBBB_CCCC_DDDD_EEEE;
        merkle_lane_valid = 1'b1;
        start_transaction = 1'b1;
        #10;
        start_transaction = 1'b0;
        #20;
        merkle_lane_valid = 1'b0;

        #10;
        expected_merkle_seed = {k_prov[247:0], k_prov[255:248]}
            ^ {192'd0, k_value}
            ^ {224'd0, k_flags}
            ^ PROV_SALT;
        expect_true(out_valid == 1'b1, "tx3 out_valid asserted");
        expect_true(seen_transaction_done == 1'b1, "tx3 transaction_done pulse");
        expect_true(seen_fidelity_pulse == 1'b1, "tx3 master fidelity increment");
        expect_true(seen_merkle_req == 1'b1, "tx3 merkle request pulse");
        expect_true(merkle_lane_seed == expected_merkle_seed, "tx3 merkle seed fallback fold");
        expect_true(out_prov == merkle_lane_digest, "tx3 provenance sourced from merkle lane");
        expected_var = (k_variance + (k_variance >> 1) + (k_variance >> 3));
        expected_var = expected_var + ((expected_var * 4) >> 8);
        expect_true(out_variance == expected_var, "tx3 mul variance profile");
        expect_true(gum_fidelity_inc == 32'd3, "tx3 gum counter incremented");
        expect_true(provenance_depth_inc == 32'd3, "tx3 provenance counter incremented");
        expect_true(formal_coverage_inc == 32'd3, "tx3 formal counter incremented");

        if (failures != 0) begin
            $display("FAIL tb_k_axi_bridge cases=%0d", failures);
            $finish(1);
        end

        $display("OMEGA_COUNTERS kaxi_gum=%0d kaxi_prov=%0d kaxi_formal=%0d", gum_fidelity_inc, provenance_depth_inc, formal_coverage_inc);
        $display("PASS tb_k_axi_bridge");
        $finish(0);
    end
endmodule

artifacts/fpga/waveforms/tb_k_axi_bridge.vcd
$date
	Thu Feb 26 08:39:48 2026
$end
$version
	Icarus Verilog
$end
$timescale
	1ps
$end
$scope module tb_k_axi_bridge $end
$var wire 1 ! transaction_done $end
$var wire 1 " s_tvalid $end
$var wire 480 # s_tuser [479:0] $end
$var wire 1 $ s_tready $end
$var wire 64 % s_tdata [63:0] $end
$var wire 32 & provenance_depth_inc [31:0] $end
$var wire 64 ' out_variance [63:0] $end
$var wire 64 ( out_value [63:0] $end
$var wire 1 ) out_valid $end
$var wire 256 * out_prov [255:0] $end
$var wire 32 + out_flags [31:0] $end
$var wire 128 , out_conf [127:0] $end
$var wire 256 - merkle_lane_seed [255:0] $end
$var wire 1 . merkle_lane_req $end
$var wire 32 / gum_fidelity_inc [31:0] $end
$var wire 32 0 formal_coverage_inc [31:0] $end
$var wire 32 1 fidelity_increment [31:0] $end
$var parameter 256 2 PROV_SALT $end
$var reg 1 3 clk $end
$var reg 64 4 conf_alpha [63:0] $end
$var reg 64 5 conf_beta [63:0] $end
$var reg 1 6 downstream_ready $end
$var reg 1024 7 dumpfile_path [1023:0] $end
$var reg 256 8 expected_merkle_seed [255:0] $end
$var reg 64 9 expected_var [63:0] $end
$var reg 128 : k_conf [127:0] $end
$var reg 32 ; k_flags [31:0] $end
$var reg 256 < k_prov [255:0] $end
$var reg 64 = k_value [63:0] $end
$var reg 64 > k_variance [63:0] $end
$var reg 256 ? merkle_lane_digest [255:0] $end
$var reg 1 @ merkle_lane_valid $end
$var reg 1 A rst_n $end
$var reg 1 B seen_fidelity_pulse $end
$var reg 1 C seen_merkle_req $end
$var reg 1 D seen_transaction_done $end
$var reg 1 E start_transaction $end
$var integer 32 F failures [31:0] $end
$scope module u_master $end
$var wire 128 G k_conf [127:0] $end
$var wire 32 H k_flags [31:0] $end
$var wire 256 I k_prov [255:0] $end
$var wire 64 J k_value [63:0] $end
$var wire 64 K k_variance [63:0] $end
$var wire 1 3 s_axi_aclk $end
$var wire 1 A s_axi_aresetn $end
$var wire 1 E start_transaction $end
$var wire 1 $ s_axi_tready $end
$var parameter 32 L CONF_WIDTH $end
$var parameter 32 M DATA_WIDTH $end
$var parameter 32 N FLAGS_WIDTH $end
$var parameter 35 O KUSER_WIDTH $end
$var parameter 32 P PROV_WIDTH $end
$var parameter 32 Q VAR_WIDTH $end
$var reg 32 R fidelity_increment [31:0] $end
$var reg 1 S pending $end
$var reg 64 T s_axi_tdata [63:0] $end
$var reg 480 U s_axi_tuser [479:0] $end
$var reg 1 " s_axi_tvalid $end
$var reg 1 ! transaction_done $end
$upscope $end
$scope module u_slave $end
$var wire 1 V accept $end
$var wire 1 3 aclk $end
$var wire 1 A aresetn $end
$var wire 1 6 downstream_ready $end
$var wire 256 W merkle_lane_digest [255:0] $end
$var wire 1 @ merkle_lane_valid $end
$var wire 64 X s_tdata [63:0] $end
$var wire 1 $ s_tready $end
$var wire 480 Y s_tuser [479:0] $end
$var wire 1 " s_tvalid $end
$var wire 8 Z success_inc [7:0] $end
$var wire 4 [ op_kind [3:0] $end
$var wire 256 \ merkle_core_digest [255:0] $end
$var wire 64 ] in_variance [63:0] $end
$var wire 256 ^ in_prov [255:0] $end
$var wire 32 _ in_flags [31:0] $end
$var wire 128 ` in_conf [127:0] $end
$var wire 64 a in_beta [63:0] $end
$var wire 64 b in_alpha [63:0] $end
$var wire 8 c failure_inc [7:0] $end
$var wire 64 d beta_next_wire [63:0] $end
$var wire 8 e alpha_q8 [7:0] $end
$var wire 64 f alpha_next_wire [63:0] $end
$var parameter 32 g CONF_WIDTH $end
$var parameter 32 h DATA_WIDTH $end
$var parameter 32 i FLAGS_WIDTH $end
$var parameter 35 j KUSER_WIDTH $end
$var parameter 4 k OP_ADD $end
$var parameter 4 l OP_DIV $end
$var parameter 4 m OP_FMA $end
$var parameter 4 n OP_MUL $end
$var parameter 4 o OP_PASS $end
$var parameter 32 p PROV_WIDTH $end
$var parameter 32 q SCALE_SHIFT $end
$var parameter 32 r VAR_WIDTH $end
$var reg 128 s degradation_full [127:0] $end
$var reg 64 t degradation_var [63:0] $end
$var reg 32 u formal_coverage_inc [31:0] $end
$var reg 32 v gum_fidelity_inc [31:0] $end
$var reg 1 . merkle_lane_req $end
$var reg 256 w merkle_lane_seed [255:0] $end
$var reg 64 x op_var [63:0] $end
$var reg 128 y out_conf [127:0] $end
$var reg 32 z out_flags [31:0] $end
$var reg 256 { out_prov [255:0] $end
$var reg 1 ) out_valid $end
$var reg 64 | out_value [63:0] $end
$var reg 64 } out_variance [63:0] $end
$var reg 32 ~ provenance_depth_inc [31:0] $end
$scope module u_merkle_core $end
$var wire 256 !" digest [255:0] $end
$var wire 32 "" in_flags [31:0] $end
$var wire 256 #" in_prov [255:0] $end
$var wire 64 $" in_value [63:0] $end
$var parameter 256 %" PROV_SALT $end
$var parameter 32 &" PROV_WIDTH $end
$upscope $end
$upscope $end
$scope task expect_true $end
$var reg 1 '" cond $end
$var reg 256 (" msg [255:0] $end
$upscope $end
$upscope $end
$enddefinitions $end
$comment Show the parameter values. $end
$dumpall
b100000000 &"
b100101101011111010000010101100001001001010111110100110101000101010100100100101101001100010001010101111101000101010100000100100101010011010101000100010101001101010010010100001101011111010000100101010101010011010111110111011000110001101001011010010110100101 %"
b1000000 r
b11110 q
b100000000 p
b0 o
b10 n
b100 m
b11 l
b1 k
b111100000 j
b100000 i
b1000000 h
b10000000 g
b1000000 Q
b100000000 P
b111100000 O
b100000 N
b1000000 M
b10000000 L
b100101101011111010000010101100001001001010111110100110101000101010100100100101101001100010001010101111101000101010100000100100101010011010101000100010101001101010010010100001101011111010000100101010101010011010111110111011000110001101001011010010110100101 2
$end
#0
$dumpvars
bx ("
x'"
b0 $"
b0 #"
b0 ""
b100101101011111010000010101100001001001010111110100110101000101010100100100101101001100010001010101111101000101010100000100100101010011010101000100010101001101010010010100001101011111010000100101010101010011010111110111011000110001101001011010010110100101 !"
b0 ~
b0 }
b0 |
b0 {
b0 z
b0 y
b0 x
b0 w
b0 v
b0 u
b0 t
b0 s
b0 f
b0 e
b0 d
b0 c
b0 b
b0 a
b0 `
b0 _
b0 ^
b0 ]
b100101101011111010000010101100001001001010111110100110101000101010100100100101101001100010001010101111101000101010100000100100101010011010101000100010101001101010010010100001101011111010000100101010101010011010111110111011000110001101001011010010110100101 \
b0 [
b0 Z
b0 Y
b0 X
b0 W
0V
b0 U
b0 T
0S
b0 R
b0 K
b0 J
b0 I
b0 H
b0 G
b0 F
0E
0D
0C
0B
0A
0@
b0 ?
b0 >
b0 =
b0 <
b0 ;
b0 :
bx 9
bx 8
b110000101110010011101000110100101100110011000010110001101110100011100110010111101100110011100000110011101100001001011110111011101100001011101100110010101100110011011110111001001101101011100110010111101110100011000100101111101101011010111110110000101111000011010010101111101100010011100100110100101100100011001110110010100101110011101100110001101100100 7
06
bx 5
bx 4
03
b0 1
b0 0
b0 /
0.
b0 -
b0 ,
b0 +
b0 *
0)
b0 (
b0 '
b0 &
b0 %
1$
b0 #
0"
0!
$end
#5000
13
#10000
03
#15000
13
#20000
03
1A
#25000
13
#30000
03
1E
b1000000000100000000100000001 ;
b1000000000100000000100000001 H
b1010000000000000000000000000000000000000000000000000000000000001000110 :
b1010000000000000000000000000000000000000000000000000000000000001000110 G
b1001000110100010101100111100010011010101111001101111011110000000100010001000100100010001000100011001100110011010001000100010001010101010101010110011001100110011101110111011110001000100010001001100110011001101010101010101010111011101110111100110011001100 <
b1001000110100010101100111100010011010101111001101111011110000000100010001000100100010001000100011001100110011010001000100010001010101010101010110011001100110011101110111011110001000100010001001100110011001101010101010101010111011101110111100110011001100 I
b1000000 >
b1000000 K
b1000000000000 =
b1000000000000 J
#35000
b111111100001001001110011100001011110101100000011011110101010100010000110110100101101110011101100110110000000001000101000001110000000110001100100010001100111010001111101100101111010111110110111100110011111001111101011100110110000010011010110111100010110110 \
b111111100001001001110011100001011110101100000011011110101010100010000110110100101101110011101100110110000000001000101000001110000000110001100100010001100111010001111101100101111010111110110111100110011111001111101011100110110000010011010110111100010110110 !"
b10 t
b1001000000 s
b1001000 x
b101000 b
b1000110 a
b1 [
b1000111 d
b1 c
b101010 f
b10 Z
b1000 e
1V
b1000000 ]
b1001000110100010101100111100010011010101111001101111011110000000100010001000100100010001000100011001100110011010001000100010001010101010101010110011001100110011101110111011110001000100010001001100110011001101010101010101010111011101110111100110011001100 ^
b1001000110100010101100111100010011010101111001101111011110000000100010001000100100010001000100011001100110011010001000100010001010101010101010110011001100110011101110111011110001000100010001001100110011001101010101010101010111011101110111100110011001100 #"
b1010000000000000000000000000000000000000000000000000000000000001000110 `
b1000000000100000000100000001 _
b1000000000100000000100000001 ""
1S
1"
b10000000001000000001000000010000000000000000000000000000000000000000000000000000000000101000000000000000000000000000000000000000000000000000000000000100011000010010001101000101011001111000100110101011110011011110111100000001000100010001001000100010001000110011001100110100010001000100010101010101010101100110011001100111011101110111100010001000100010011001100110011010101010101010101110111011101111001100110011000000000000000000000000000000000000000000000000000000000001000000 #
b10000000001000000001000000010000000000000000000000000000000000000000000000000000000000101000000000000000000000000000000000000000000000000000000000000100011000010010001101000101011001111000100110101011110011011110111100000001000100010001001000100010001000110011001100110100010001000100010101010101010101100110011001100111011101110111100010001000100010011001100110011010101010101010101110111011101111001100110011000000000000000000000000000000000000000000000000000000000001000000 U
b10000000001000000001000000010000000000000000000000000000000000000000000000000000000000101000000000000000000000000000000000000000000000000000000000000100011000010010001101000101011001111000100110101011110011011110111100000001000100010001001000100010001000110011001100110100010001000100010101010101010101100110011001100111011101110111100010001000100010011001100110011010101010101010101110111011101111001100110011000000000000000000000000000000000000000000000000000000000001000000 Y
b1000000000000 %
b1000000000000 T
b1000000000000 X
b1000000000000 $"
13
#40000
03
0E
#45000
0$
0V
1)
b1 0
b1 u
b1 &
b1 ~
b1 /
b1 v
b1010100000000000000000000000000000000000000000000000000000000001000111 ,
b1010100000000000000000000000000000000000000000000000000000000001000111 y
b111111100001001001110011100001011110101100000011011110101010100010000110110100101101110011101100110110000000001000101000001110000000110001100100010001100111010001111101100101111010111110110111100110011111001111101011100110110000010011010110111100010110110 *
b111111100001001001110011100001011110101100000011011110101010100010000110110100101101110011101100110110000000001000101000001110000000110001100100010001100111010001111101100101111010111110110111100110011111001111101011100110110000010011010110111100010110110 {
1.
b111111100001001001110011100001011110101100000011011110101010100010000110110100101101110011101100110110000000001000101000001110000000110001100100010001100111010001111101100101111010111110110111100110011111001111101011100110110000010011010110111100010110110 -
b111111100001001001110011100001011110101100000011011110101010100010000110110100101101110011101100110110000000001000101000001110000000110001100100010001100111010001111101100101111010111110110111100110011111001111101011100110110000010011010110111100010110110 w
b1000000000100000000100000001 +
b1000000000100000000100000001 z
b1001010 '
b1001010 }
b1000000000000 (
b1000000000000 |
b1 1
b1 R
1!
0S
0"
13
#50000
03
#55000
b0 1
b0 R
0!
0.
1C
1B
1D
13
#60000
1$
03
16
b1000111 5
b101010 4
b11101000111100000110001001000000110011001101111011100100110110101100001011011000010000001100011011011110111010101101110011101000110010101110010 ("
1'"
b1001010 9
#65000
0)
13
#70000
03
1E
b10000000000110000000000000100 ;
b10000000000110000000000000100 H
b11001000000000000000000000000000000000000000000000000000000000011001000 :
b11001000000000000000000000000000000000000000000000000000000000011001000 G
b100000000 >
b100000000 K
b1000000000000000000000000000000000000 =
b1000000000000000000000000000000000000 J
0C
0B
0D
06
#75000
b111111100001001001110011100001011110101100000011011110101010100010000110110100101101110011101100110110000000001000101000001110000000110001100100010001100111010001111101100101111010111110110111100110011111001111101011101110110011010011010100110100110110011 \
b111111100001001001110011100001011110101100000011011110101010100010000110110100101101110011101100110110000000001000101000001110000000110001100100010001100111010001111101100101111010111110110111100110011111001111101011101110110011010011010100110100110110011 !"
b11101 t
b1110100000000 s
b111010000 x
b1100100 b
b11001000 a
b100 [
b11001000 d
b0 c
b1100111 f
b11 Z
b10000 e
1V
b100000000 ]
b11001000000000000000000000000000000000000000000000000000000000011001000 `
b10000000000110000000000000100 _
b10000000000110000000000000100 ""
1S
1"
b100000000001100000000000001000000000000000000000000000000000000000000000000000000000001100100000000000000000000000000000000000000000000000000000000001100100000010010001101000101011001111000100110101011110011011110111100000001000100010001001000100010001000110011001100110100010001000100010101010101010101100110011001100111011101110111100010001000100010011001100110011010101010101010101110111011101111001100110011000000000000000000000000000000000000000000000000000000000100000000 #
b100000000001100000000000001000000000000000000000000000000000000000000000000000000000001100100000000000000000000000000000000000000000000000000000000001100100000010010001101000101011001111000100110101011110011011110111100000001000100010001001000100010001000110011001100110100010001000100010101010101010101100110011001100111011101110111100010001000100010011001100110011010101010101010101110111011101111001100110011000000000000000000000000000000000000000000000000000000000100000000 U
b100000000001100000000000001000000000000000000000000000000000000000000000000000000000001100100000000000000000000000000000000000000000000000000000000001100100000010010001101000101011001111000100110101011110011011110111100000001000100010001001000100010001000110011001100110100010001000100010101010101010101100110011001100111011101110111100010001000100010011001100110011010101010101010101110111011101111001100110011000000000000000000000000000000000000000000000000000000000100000000 Y
b1000000000000000000000000000000000000 %
b1000000000000000000000000000000000000 T
b1000000000000000000000000000000000000 X
b1000000000000000000000000000000000000 $"
13
#80000
03
0E
