hardware/fpga/k_axi_return_fifo.v
// GENERATED_FROM_STDLIB: stdlib/hardware/kaxi.sio
// GENERATED_BY: self-hosted/compiler/codegen/hardware/kaxi_emitter.sio
// K-AXI bidirectional return FIFO (deterministic fixed-width queue).

`timescale 1ns/1ps

module k_axi_return_fifo #(
    parameter WIDTH = 544,
    parameter DEPTH = 8,
    parameter ADDR_BITS = 3
) (
    input  wire                  clk,
    input  wire                  rst_n,
    input  wire                  wr_en,
    input  wire [WIDTH-1:0]      wr_data,
    output wire                  full,
    output reg                   overflow,
    input  wire                  rd_en,
    output wire [WIDTH-1:0]      rd_data,
    output wire                  empty,
    output reg                   underflow,
    output reg  [ADDR_BITS:0]    count
);
    localparam integer DEPTH_INT = DEPTH;

    reg [WIDTH-1:0] mem [0:DEPTH-1];
    reg [ADDR_BITS-1:0] wptr;
    reg [ADDR_BITS-1:0] rptr;

    assign full = (count == DEPTH_INT);
    assign empty = (count == 0);
    assign rd_data = mem[rptr];

    wire do_write = wr_en && !full;
    wire do_read = rd_en && !empty;

    always @(posedge clk or negedge rst_n) begin
        if (!rst_n) begin
            wptr <= {ADDR_BITS{1'b0}};
            rptr <= {ADDR_BITS{1'b0}};
            count <= {(ADDR_BITS + 1){1'b0}};
            overflow <= 1'b0;
            underflow <= 1'b0;
        end else begin
            overflow <= 1'b0;
            underflow <= 1'b0;

            if (wr_en && full) begin
                overflow <= 1'b1;
            end
            if (rd_en && empty) begin
                underflow <= 1'b1;
            end

            if (do_write) begin
                mem[wptr] <= wr_data;
                wptr <= wptr + 1'b1;
            end

            if (do_read) begin
                rptr <= rptr + 1'b1;
            end

            case ({do_write, do_read})
                2'b10: count <= count + 1'b1;
                2'b01: count <= count - 1'b1;
                default: count <= count;
            endcase
        end
    end
endmodule

hardware/fpga/k_axi_return_mux.v
// GENERATED_FROM_STDLIB: stdlib/hardware/kaxi.sio
// GENERATED_BY: self-hosted/compiler/codegen/hardware/kaxi_emitter.sio
// K-AXI bidirectional return mux: fabric -> return FIFO -> host runtime.

`timescale 1ns/1ps

module k_axi_return_mux #(
    parameter PACKET_WIDTH = 544,
    parameter FIFO_DEPTH = 8,
    parameter FIFO_ADDR_BITS = 3
) (
    input  wire                  aclk,
    input  wire                  aresetn,

    // Inbound return lane from epistemic fabric.
    input  wire                  fabric_valid,
    output wire                  fabric_ready,
    input  wire [7:0]            kind,
    input  wire [7:0]            status,
    input  wire [7:0]            op_kind,
    input  wire [7:0]            flags,
    input  wire [31:0]           tx_seq,
    input  wire [31:0]           fidelity_inc,
    input  wire [31:0]           prov_depth_inc,
    input  wire [31:0]           formal_cov_inc,
    input  wire [63:0]           epi_log_q32_32,
    input  wire [255:0]          digest,
    input  wire [63:0]           timestamp_cycles,

    // Outbound lane to host/runtime consumer.
    output wire                  ret_valid,
    input  wire                  ret_ready,
    output wire [PACKET_WIDTH-1:0] ret_data,

    // Telemetry counters.
    output reg  [31:0]           accepted_packets,
    output reg  [31:0]           dropped_packets,
    output reg  [31:0]           overflow_events
);
    wire [PACKET_WIDTH-1:0] packet_in;
    assign packet_in = {
        timestamp_cycles,
        digest,
        epi_log_q32_32,
        formal_cov_inc,
        prov_depth_inc,
        fidelity_inc,
        tx_seq,
        flags,
        op_kind,
        status,
        kind
    };

    wire fifo_full;
    wire fifo_empty;
    wire fifo_overflow;
    wire fifo_underflow;
    wire [FIFO_ADDR_BITS:0] fifo_count;
    wire [PACKET_WIDTH-1:0] fifo_rd_data;

    assign fabric_ready = !fifo_full;

    wire wr_en = fabric_valid && fabric_ready;
    wire rd_en = ret_ready && !fifo_empty;

    assign ret_valid = !fifo_empty;
    assign ret_data = fifo_rd_data;

    k_axi_return_fifo #(
        .WIDTH(PACKET_WIDTH),
        .DEPTH(FIFO_DEPTH),
        .ADDR_BITS(FIFO_ADDR_BITS)
    ) u_return_fifo (
        .clk(aclk),
        .rst_n(aresetn),
        .wr_en(wr_en),
        .wr_data(packet_in),
        .full(fifo_full),
        .overflow(fifo_overflow),
        .rd_en(rd_en),
        .rd_data(fifo_rd_data),
        .empty(fifo_empty),
        .underflow(fifo_underflow),
        .count(fifo_count)
    );

    always @(posedge aclk or negedge aresetn) begin
        if (!aresetn) begin
            accepted_packets <= 32'd0;
            dropped_packets <= 32'd0;
            overflow_events <= 32'd0;
        end else begin
            if (wr_en) begin
                accepted_packets <= accepted_packets + 32'd1;
            end
            if (fabric_valid && !fabric_ready) begin
                dropped_packets <= dropped_packets + 32'd1;
            end
            if (fifo_overflow) begin
                overflow_events <= overflow_events + 32'd1;
            end
            if (fifo_underflow) begin
                overflow_events <= overflow_events + 32'd1;
            end
        end
    end
endmodule

hardware/fpga/tb_k_axi_bidirectional.v
`timescale 1ns/1ps

module tb_k_axi_bidirectional;
    reg aclk = 1'b0;
    reg aresetn = 1'b0;
    always #5 aclk = ~aclk;

    reg fabric_valid;
    wire fabric_ready;
    reg [7:0] kind;
    reg [7:0] status;
    reg [7:0] op_kind;
    reg [7:0] flags;
    reg [31:0] tx_seq;
    reg [31:0] fidelity_inc;
    reg [31:0] prov_depth_inc;
    reg [31:0] formal_cov_inc;
    reg [63:0] epi_log_q32_32;
    reg [255:0] digest;
    reg [63:0] timestamp_cycles;

    wire ret_valid;
    reg ret_ready;
    wire [543:0] ret_data;

    wire [31:0] accepted_packets;
    wire [31:0] dropped_packets;
    wire [31:0] overflow_events;

    integer failures;
    integer drained;
    reg [31:0] first_seq;

    k_axi_return_mux #(
        .PACKET_WIDTH(544),
        .FIFO_DEPTH(4),
        .FIFO_ADDR_BITS(2)
    ) dut (
        .aclk(aclk),
        .aresetn(aresetn),
        .fabric_valid(fabric_valid),
        .fabric_ready(fabric_ready),
        .kind(kind),
        .status(status),
        .op_kind(op_kind),
        .flags(flags),
        .tx_seq(tx_seq),
        .fidelity_inc(fidelity_inc),
        .prov_depth_inc(prov_depth_inc),
        .formal_cov_inc(formal_cov_inc),
        .epi_log_q32_32(epi_log_q32_32),
        .digest(digest),
        .timestamp_cycles(timestamp_cycles),
        .ret_valid(ret_valid),
        .ret_ready(ret_ready),
        .ret_data(ret_data),
        .accepted_packets(accepted_packets),
        .dropped_packets(dropped_packets),
        .overflow_events(overflow_events)
    );

    task send_packet(input [31:0] seq, input [7:0] op);
    begin
        @(posedge aclk);
        fabric_valid <= 1'b1;
        kind <= 8'hA1;
        status <= 8'h01;
        op_kind <= op;
        flags <= 8'h5A;
        tx_seq <= seq;
        fidelity_inc <= 32'd1;
        prov_depth_inc <= 32'd1;
        formal_cov_inc <= 32'd1;
        epi_log_q32_32 <= {32'd0, seq};
        digest <= {224'd0, seq};
        timestamp_cycles <= 64'h1000 + seq;

        @(posedge aclk);
        fabric_valid <= 1'b0;
    end
    endtask

    initial begin
        failures = 0;
        drained = 0;
        first_seq = 32'd0;
        fabric_valid = 1'b0;
        kind = 8'd0;
        status = 8'd0;
        op_kind = 8'd0;
        flags = 8'd0;
        tx_seq = 32'd0;
        fidelity_inc = 32'd0;
        prov_depth_inc = 32'd0;
        formal_cov_inc = 32'd0;
        epi_log_q32_32 = 64'd0;
        digest = 256'd0;
        timestamp_cycles = 64'd0;
        ret_ready = 1'b0;

        $dumpfile("artifacts/fpga/waveforms/tb_k_axi_bidirectional.vcd");
        $dumpvars(0, tb_k_axi_bidirectional);

        repeat (4) @(posedge aclk);
        aresetn = 1'b1;
        repeat (2) @(posedge aclk);

        // Fill FIFO and force one overflow/drop packet.
        send_packet(32'd1, 8'h11);
        send_packet(32'd2, 8'h12);
        send_packet(32'd3, 8'h13);
        send_packet(32'd4, 8'h14);
        send_packet(32'd5, 8'h15);

        repeat (2) @(posedge aclk);
        if (accepted_packets !== 32'd4) begin
            $display("ASSERT FAIL: accepted_packets expected 4 got %0d", accepted_packets);
            failures = failures + 1;
        end
        if (dropped_packets !== 32'd1) begin
            $display("ASSERT FAIL: dropped_packets expected 1 got %0d", dropped_packets);
            failures = failures + 1;
        end

        // Drain queue.
        ret_ready = 1'b1;
        while (drained < 4) begin
            @(posedge aclk);
            if (ret_valid && ret_ready) begin
                if (drained == 0) begin
                    first_seq = ret_data[63:32];
                end
                drained = drained + 1;
            end
        end

        if (first_seq !== 32'd1) begin
            $display("ASSERT FAIL: first packet tx_seq expected 1 got %0d", first_seq);
            failures = failures + 1;
        end
        if (overflow_events == 0) begin
            $display("ASSERT FAIL: overflow_events should be > 0");
            failures = failures + 1;
        end

        $display(
            "OMEGA_COUNTERS kaxi_return_seen=%0d kaxi_return_dropped=%0d kaxi_return_overflow=%0d",
            accepted_packets,
            dropped_packets,
            overflow_events
        );

        if (failures > 0) begin
            $display("FAIL tb_k_axi_bidirectional cases=%0d", failures);
            $finish(1);
        end

        $display("PASS tb_k_axi_bidirectional");
        $finish(0);
    end
endmodule

artifacts/fpga/waveforms/tb_k_axi_bidirectional.vcd
$date
	Tue Feb 24 23:13:28 2026
$end
$version
	Icarus Verilog
$end
$timescale
	1ps
$end
$scope module tb_k_axi_bidirectional $end
$var wire 1 ! ret_valid $end
$var wire 544 " ret_data [543:0] $end
$var wire 32 # overflow_events [31:0] $end
$var wire 1 $ fabric_ready $end
$var wire 32 % dropped_packets [31:0] $end
$var wire 32 & accepted_packets [31:0] $end
$var reg 1 ' aclk $end
$var reg 1 ( aresetn $end
$var reg 256 ) digest [255:0] $end
$var reg 64 * epi_log_q32_32 [63:0] $end
$var reg 1 + fabric_valid $end
$var reg 32 , fidelity_inc [31:0] $end
$var reg 32 - first_seq [31:0] $end
$var reg 8 . flags [7:0] $end
$var reg 32 / formal_cov_inc [31:0] $end
$var reg 8 0 kind [7:0] $end
$var reg 8 1 op_kind [7:0] $end
$var reg 32 2 prov_depth_inc [31:0] $end
$var reg 1 3 ret_ready $end
$var reg 8 4 status [7:0] $end
$var reg 64 5 timestamp_cycles [63:0] $end
$var reg 32 6 tx_seq [31:0] $end
$var integer 32 7 drained [31:0] $end
$var integer 32 8 failures [31:0] $end
$scope module dut $end
$var wire 1 ' aclk $end
$var wire 1 ( aresetn $end
$var wire 256 9 digest [255:0] $end
$var wire 64 : epi_log_q32_32 [63:0] $end
$var wire 1 + fabric_valid $end
$var wire 32 ; fidelity_inc [31:0] $end
$var wire 8 < flags [7:0] $end
$var wire 32 = formal_cov_inc [31:0] $end
$var wire 8 > kind [7:0] $end
$var wire 8 ? op_kind [7:0] $end
$var wire 32 @ prov_depth_inc [31:0] $end
$var wire 1 A rd_en $end
$var wire 544 B ret_data [543:0] $end
$var wire 1 3 ret_ready $end
$var wire 8 C status [7:0] $end
$var wire 64 D timestamp_cycles [63:0] $end
$var wire 32 E tx_seq [31:0] $end
$var wire 1 F wr_en $end
$var wire 1 ! ret_valid $end
$var wire 544 G packet_in [543:0] $end
$var wire 1 H fifo_underflow $end
$var wire 544 I fifo_rd_data [543:0] $end
$var wire 1 J fifo_overflow $end
$var wire 1 K fifo_full $end
$var wire 1 L fifo_empty $end
$var wire 3 M fifo_count [2:0] $end
$var wire 1 $ fabric_ready $end
$var parameter 32 N FIFO_ADDR_BITS $end
$var parameter 32 O FIFO_DEPTH $end
$var parameter 32 P PACKET_WIDTH $end
$var reg 32 Q accepted_packets [31:0] $end
$var reg 32 R dropped_packets [31:0] $end
$var reg 32 S overflow_events [31:0] $end
$scope module u_return_fifo $end
$var wire 1 ' clk $end
$var wire 1 T do_read $end
$var wire 1 U do_write $end
$var wire 544 V rd_data [543:0] $end
$var wire 1 A rd_en $end
$var wire 1 ( rst_n $end
$var wire 544 W wr_data [543:0] $end
$var wire 1 F wr_en $end
$var wire 1 K full $end
$var wire 1 L empty $end
$var parameter 32 X ADDR_BITS $end
$var parameter 32 Y DEPTH $end
$var parameter 32 Z DEPTH_INT $end
$var parameter 32 [ WIDTH $end
$var reg 3 \ count [2:0] $end
$var reg 1 J overflow $end
$var reg 2 ] rptr [1:0] $end
$var reg 1 H underflow $end
$var reg 2 ^ wptr [1:0] $end
$upscope $end
$upscope $end
$scope task send_packet $end
$var reg 8 _ op [7:0] $end
$var reg 32 ` seq [31:0] $end
$upscope $end
$upscope $end
$enddefinitions $end
$comment Show the parameter values. $end
$dumpall
b1000100000 [
b100 Z
b100 Y
b10 X
b1000100000 P
b100 O
b10 N
$end
#0
$dumpvars
bx `
bx _
b0 ^
b0 ]
b0 \
b0 W
bx V
0U
0T
b0 S
b0 R
b0 Q
b0 M
1L
0K
0J
bx I
0H
b0 G
0F
b0 E
b0 D
b0 C
bx B
0A
b0 @
b0 ?
b0 >
b0 =
b0 <
b0 ;
b0 :
b0 9
b0 8
b0 7
b0 6
b0 5
b0 4
03
b0 2
b0 1
b0 0
b0 /
b0 .
b0 -
b0 ,
0+
b0 *
b0 )
0(
0'
b0 &
b0 %
1$
b0 #
bx "
0!
$end
#5000
1'
#10000
0'
#15000
1'
#20000
0'
#25000
1'
#30000
0'
#35000
1(
1'
#40000
0'
#45000
1'
#50000
0'
#55000
b10001 _
b1 `
1'
#60000
0'
#65000
1U
1F
b1000000000001 5
b1000000000001 D
b1 )
b1 9
b1 *
b1 :
b1 /
b1 =
b1 2
b1 @
b1 ,
b1 ;
b1 6
b1 E
b1011010 .
b1011010 <
b10001 1
b10001 ?
b1 4
b1 C
b1000000000001000000000000000000000000000000000000000000000000000000000000000000000000000000000000000000000000000000000000000000000000000000000000000000000000000000000000000000000000000000000000000000000000000000000000000000000000000000000000000000000000000000000000000100000000000000000000000000000000000000000000000000000000000000010000000000000000000000000000000100000000000000000000000000000001000000000000000000000000000000010000000000000000000000000000000101011010000100010000000110100001 G
b1000000000001000000000000000000000000000000000000000000000000000000000000000000000000000000000000000000000000000000000000000000000000000000000000000000000000000000000000000000000000000000000000000000000000000000000000000000000000000000000000000000000000000000000000000100000000000000000000000000000000000000000000000000000000000000010000000000000000000000000000000100000000000000000000000000000001000000000000000000000000000000010000000000000000000000000000000101011010000100010000000110100001 W
b10100001 0
b10100001 >
1+
1'
#70000
0'
#75000
0U
0F
1!
0L
b1 M
b1 \
b1 ^
b1000000000001000000000000000000000000000000000000000000000000000000000000000000000000000000000000000000000000000000000000000000000000000000000000000000000000000000000000000000000000000000000000000000000000000000000000000000000000000000000000000000000000000000000000000100000000000000000000000000000000000000000000000000000000000000010000000000000000000000000000000100000000000000000000000000000001000000000000000000000000000000010000000000000000000000000000000101011010000100010000000110100001 "
b1000000000001000000000000000000000000000000000000000000000000000000000000000000000000000000000000000000000000000000000000000000000000000000000000000000000000000000000000000000000000000000000000000000000000000000000000000000000000000000000000000000000000000000000000000100000000000000000000000000000000000000000000000000000000000000010000000000000000000000000000000100000000000000000000000000000001000000000000000000000000000000010000000000000000000000000000000101011010000100010000000110100001 B
b1000000000001000000000000000000000000000000000000000000000000000000000000000000000000000000000000000000000000000000000000000000000000000000000000000000000000000000000000000000000000000000000000000000000000000000000000000000000000000000000000000000000000000000000000000100000000000000000000000000000000000000000000000000000000000000010000000000000000000000000000000100000000000000000000000000000001000000000000000000000000000000010000000000000000000000000000000101011010000100010000000110100001 I
b1000000000001000000000000000000000000000000000000000000000000000000000000000000000000000000000000000000000000000000000000000000000000000000000000000000000000000000000000000000000000000000000000000000000000000000000000000000000000000000000000000000000000000000000000000100000000000000000000000000000000000000000000000000000000000000010000000000000000000000000000000100000000000000000000000000000001000000000000000000000000000000010000000000000000000000000000000101011010000100010000000110100001 V
b1 &
b1 Q
0+
b10010 _
b10 `
1'
#80000
0'
#85000
1U
1F
b1000000000010 5
b1000000000010 D
b10 )
b10 9
b10 *
b10 :
b10 6
b10 E
b1000000000010000000000000000000000000000000000000000000000000000000000000000000000000000000000000000000000000000000000000000000000000000000000000000000000000000000000000000000000000000000000000000000000000000000000000000000000000000000000000000000000000000000000000001000000000000000000000000000000000000000000000000000000000000000100000000000000000000000000000000100000000000000000000000000000001000000000000000000000000000000010000000000000000000000000000001001011010000100100000000110100001 G
b1000000000010000000000000000000000000000000000000000000000000000000000000000000000000000000000000000000000000000000000000000000000000000000000000000000000000000000000000000000000000000000000000000000000000000000000000000000000000000000000000000000000000000000000000001000000000000000000000000000000000000000000000000000000000000000100000000000000000000000000000000100000000000000000000000000000001000000000000000000000000000000010000000000000000000000000000001001011010000100100000000110100001 W
b10010 1
b10010 ?
1+
1'
#90000
0'
#95000
0U
0F
b10 M
b10 \
b10 ^
b10 &
b10 Q
0+
b10011 _
b11 `
1'
#100000
0'
#105000
1U
1F
b1000000000011 5
b1000000000011 D
b11 )
b11 9
b11 *
b11 :
b11 6
b11 E
b1000000000011000000000000000000000000000000000000000000000000000000000000000000000000000000000000000000000000000000000000000000000000000000000000000000000000000000000000000000000000000000000000000000000000000000000000000000000000000000000000000000000000000000000000001100000000000000000000000000000000000000000000000000000000000000110000000000000000000000000000000100000000000000000000000000000001000000000000000000000000000000010000000000000000000000000000001101011010000100110000000110100001 G
b1000000000011000000000000000000000000000000000000000000000000000000000000000000000000000000000000000000000000000000000000000000000000000000000000000000000000000000000000000000000000000000000000000000000000000000000000000000000000000000000000000000000000000000000000001100000000000000000000000000000000000000000000000000000000000000110000000000000000000000000000000100000000000000000000000000000001000000000000000000000000000000010000000000000000000000000000001101011010000100110000000110100001 W
b10011 1
b10011 ?
1+
1'
#110000
0'
#115000
0U
0F
b11 M
b11 \
b11 ^
b11 &
b11 Q
0+
b10100 _
b100 `
1'
#120000
0'
#125000
1U
1F
b1000000000100 5
b1000000000100 D
b100 )
b100 9
b100 *
b100 :
b100 6
b100 E
b1000000000100000000000000000000000000000000000000000000000000000000000000000000000000000000000000000000000000000000000000000000000000000000000000000000000000000000000000000000000000000000000000000000000000000000000000000000000000000000000000000000000000000000000000010000000000000000000000000000000000000000000000000000000000000001000000000000000000000000000000000100000000000000000000000000000001000000000000000000000000000000010000000000000000000000000000010001011010000101000000000110100001 G
b1000000000100000000000000000000000000000000000000000000000000000000000000000000000000000000000000000000000000000000000000000000000000000000000000000000000000000000000000000000000000000000000000000000000000000000000000000000000000000000000000000000000000000000000000010000000000000000000000000000000000000000000000000000000000000001000000000000000000000000000000000100000000000000000000000000000001000000000000000000000000000000010000000000000000000000000000010001011010000101000000000110100001 W
b10100 1
b10100 ?
1+
1'
#130000
0'
#135000
0U
0F
0$
1K
b100 M
b100 \
b0 ^
b100 &
b100 Q
0+
b10101 _
b101 `
1'
#140000
0'
#145000
b1000000000101 5
b1000000000101 D
b101 )
b101 9
b101 *
b101 :
b101 6
b101 E
b1000000000101000000000000000000000000000000000000000000000000000000000000000000000000000000000000000000000000000000000000000000000000000000000000000000000000000000000000000000000000000000000000000000000000000000000000000000000000000000000000000000000000000000000000010100000000000000000000000000000000000000000000000000000000000001010000000000000000000000000000000100000000000000000000000000000001000000000000000000000000000000010000000000000000000000000000010101011010000101010000000110100001 G
b1000000000101000000000000000000000000000000000000000000000000000000000000000000000000000000000000000000000000000000000000000000000000000000000000000000000000000000000000000000000000000000000000000000000000000000000000000000000000000000000000000000000000000000000000010100000000000000000000000000000000000000000000000000000000000001010000000000000000000000000000000100000000000000000000000000000001000000000000000000000000000000010000000000000000000000000000010101011010000101010000000110100001 W
b10101 1
b10101 ?
1+
1'
#150000
0'
#155000
b1 %
b1 R
0+
1'
#160000
0'
#165000
1'
#170000
0'
#175000
1T
1A
13
1'
#180000
0'
#185000
1$
0K
b11 M
b11 \
b1000000000010000000000000000000000000000000000000000000000000000000000000000000000000000000000000000000000000000000000000000000000000000000000000000000000000000000000000000000000000000000000000000000000000000000000000000000000000000000000000000000000000000000000000001000000000000000000000000000000000000000000000000000000000000000100000000000000000000000000000000100000000000000000000000000000001000000000000000000000000000000010000000000000000000000000000001001011010000100100000000110100001 "
b1000000000010000000000000000000000000000000000000000000000000000000000000000000000000000000000000000000000000000000000000000000000000000000000000000000000000000000000000000000000000000000000000000000000000000000000000000000000000000000000000000000000000000000000000001000000000000000000000000000000000000000000000000000000000000000100000000000000000000000000000000100000000000000000000000000000001000000000000000000000000000000010000000000000000000000000000001001011010000100100000000110100001 B
b1000000000010000000000000000000000000000000000000000000000000000000000000000000000000000000000000000000000000000000000000000000000000000000000000000000000000000000000000000000000000000000000000000000000000000000000000000000000000000000000000000000000000000000000000001000000000000000000000000000000000000000000000000000000000000000100000000000000000000000000000000100000000000000000000000000000001000000000000000000000000000000010000000000000000000000000000001001011010000100100000000110100001 I
b1000000000010000000000000000000000000000000000000000000000000000000000000000000000000000000000000000000000000000000000000000000000000000000000000000000000000000000000000000000000000000000000000000000000000000000000000000000000000000000000000000000000000000000000000001000000000000000000000000000000000000000000000000000000000000000100000000000000000000000000000000100000000000000000000000000000001000000000000000000000000000000010000000000000000000000000000001001011010000100100000000110100001 V
b1 ]
b1 7
b1 -
1'
#190000
0'
#195000
b10 M
b10 \
b1000000000011000000000000000000000000000000000000000000000000000000000000000000000000000000000000000000000000000000000000000000000000000000000000000000000000000000000000000000000000000000000000000000000000000000000000000000000000000000000000000000000000000000000000001100000000000000000000000000000000000000000000000000000000000000110000000000000000000000000000000100000000000000000000000000000001000000000000000000000000000000010000000000000000000000000000001101011010000100110000000110100001 "
b1000000000011000000000000000000000000000000000000000000000000000000000000000000000000000000000000000000000000000000000000000000000000000000000000000000000000000000000000000000000000000000000000000000000000000000000000000000000000000000000000000000000000000000000000001100000000000000000000000000000000000000000000000000000000000000110000000000000000000000000000000100000000000000000000000000000001000000000000000000000000000000010000000000000000000000000000001101011010000100110000000110100001 B
b1000000000011000000000000000000000000000000000000000000000000000000000000000000000000000000000000000000000000000000000000000000000000000000000000000000000000000000000000000000000000000000000000000000000000000000000000000000000000000000000000000000000000000000000000001100000000000000000000000000000000000000000000000000000000000000110000000000000000000000000000000100000000000000000000000000000001000000000000000000000000000000010000000000000000000000000000001101011010000100110000000110100001 I
b1000000000011000000000000000000000000000000000000000000000000000000000000000000000000000000000000000000000000000000000000000000000000000000000000000000000000000000000000000000000000000000000000000000000000000000000000000000000000000000000000000000000000000000000000001100000000000000000000000000000000000000000000000000000000000000110000000000000000000000000000000100000000000000000000000000000001000000000000000000000000000000010000000000000000000000000000001101011010000100110000000110100001 V
b10 ]
b10 7
1'
#200000
0'
#205000
b1 M
b1 \
b1000000000100000000000000000000000000000000000000000000000000000000000000000000000000000000000000000000000000000000000000000000000000000000000000000000000000000000000000000000000000000000000000000000000000000000000000000000000000000000000000000000000000000000000000010000000000000000000000000000000000000000000000000000000000000001000000000000000000000000000000000100000000000000000000000000000001000000000000000000000000000000010000000000000000000000000000010001011010000101000000000110100001 "
b1000000000100000000000000000000000000000000000000000000000000000000000000000000000000000000000000000000000000000000000000000000000000000000000000000000000000000000000000000000000000000000000000000000000000000000000000000000000000000000000000000000000000000000000000010000000000000000000000000000000000000000000000000000000000000001000000000000000000000000000000000100000000000000000000000000000001000000000000000000000000000000010000000000000000000000000000010001011010000101000000000110100001 B
b1000000000100000000000000000000000000000000000000000000000000000000000000000000000000000000000000000000000000000000000000000000000000000000000000000000000000000000000000000000000000000000000000000000000000000000000000000000000000000000000000000000000000000000000000010000000000000000000000000000000000000000000000000000000000000001000000000000000000000000000000000100000000000000000000000000000001000000000000000000000000000000010000000000000000000000000000010001011010000101000000000110100001 I
b1000000000100000000000000000000000000000000000000000000000000000000000000000000000000000000000000000000000000000000000000000000000000000000000000000000000000000000000000000000000000000000000000000000000000000000000000000000000000000000000000000000000000000000000000010000000000000000000000000000000000000000000000000000000000000001000000000000000000000000000000000100000000000000000000000000000001000000000000000000000000000000010000000000000000000000000000010001011010000101000000000110100001 V
b11 ]
b11 7
1'
#210000
0'
#215000
0T
0A
0!
1L
b0 M
b0 \
b1000000000001000000000000000000000000000000000000000000000000000000000000000000000000000000000000000000000000000000000000000000000000000000000000000000000000000000000000000000000000000000000000000000000000000000000000000000000000000000000000000000000000000000000000000100000000000000000000000000000000000000000000000000000000000000010000000000000000000000000000000100000000000000000000000000000001000000000000000000000000000000010000000000000000000000000000000101011010000100010000000110100001 "
b1000000000001000000000000000000000000000000000000000000000000000000000000000000000000000000000000000000000000000000000000000000000000000000000000000000000000000000000000000000000000000000000000000000000000000000000000000000000000000000000000000000000000000000000000000100000000000000000000000000000000000000000000000000000000000000010000000000000000000000000000000100000000000000000000000000000001000000000000000000000000000000010000000000000000000000000000000101011010000100010000000110100001 B
b1000000000001000000000000000000000000000000000000000000000000000000000000000000000000000000000000000000000000000000000000000000000000000000000000000000000000000000000000000000000000000000000000000000000000000000000000000000000000000000000000000000000000000000000000000100000000000000000000000000000000000000000000000000000000000000010000000000000000000000000000000100000000000000000000000000000001000000000000000000000000000000010000000000000000000000000000000101011010000100010000000110100001 I
b1000000000001000000000000000000000000000000000000000000000000000000000000000000000000000000000000000000000000000000000000000000000000000000000000000000000000000000000000000000000000000000000000000000000000000000000000000000000000000000000000000000000000000000000000000100000000000000000000000000000000000000000000000000000000000000010000000000000000000000000000000100000000000000000000000000000001000000000000000000000000000000010000000000000000000000000000000101011010000100010000000110100001 V
b0 ]
b1 8
b100 7
1'
